collective.tiles.sliders-1.0.0-py2.7-nspkg.pth
collective/tiles/sliders/__init__.py
collective/tiles/sliders/base.py
collective/tiles/sliders/config.py
collective/tiles/sliders/configure.zcml
collective/tiles/sliders/interfaces.py
collective/tiles/sliders/profiles.zcml
collective/tiles/sliders/setuphandlers.py
collective/tiles/sliders/testing.py
collective/tiles/sliders/upgrades.py
collective/tiles/sliders/upgrades.zcml
collective/tiles/sliders/utils.py
collective/tiles/sliders/widget.py
collective/tiles/sliders/locales/collective.tiles.sliders.pot
collective/tiles/sliders/locales/update.sh
collective/tiles/sliders/profiles/default/browserlayer.xml
collective/tiles/sliders/profiles/default/metadata.xml
collective/tiles/sliders/profiles/default/registry.xml
collective/tiles/sliders/profiles/mosaic_support/metadata.xml
collective/tiles/sliders/profiles/mosaic_support/registry.xml
collective/tiles/sliders/profiles/uninstall/browserlayer.xml
collective/tiles/sliders/profiles/uninstall/registry.xml
collective/tiles/sliders/static/collective.tiles.sliders.dynamicform-compiled.js
collective/tiles/sliders/static/compiled.min.js
collective/tiles/sliders/static/compiled.min.js.map
collective/tiles/sliders/static/pattern.js
collective/tiles/sliders/tests/__init__.py
collective/tiles/sliders/tests/test_robot.py
collective/tiles/sliders/tests/test_setup.py
collective/tiles/sliders/tests/robot/test_setup.robot
collective/tiles/sliders/tiles/__init__.py
collective/tiles/sliders/tiles/configure.zcml
collective/tiles/sliders/tiles/responsiveslides/__init__.py
collective/tiles/sliders/tiles/responsiveslides/configure.zcml
collective/tiles/sliders/tiles/responsiveslides/tile.pt
collective/tiles/sliders/tiles/responsiveslides/tile.py
collective/tiles/sliders/tiles/responsiveslides/assets/buttons.gif
collective/tiles/sliders/tiles/responsiveslides/assets/collective.tiles.sliders.responsiveslides-compiled.js
collective/tiles/sliders/tiles/responsiveslides/assets/compiled.css
collective.tiles.sliders-1.0.0.dist-info/METADATA
collective.tiles.sliders-1.0.0.dist-info/WHEEL
collective.tiles.sliders-1.0.0.dist-info/entry_points.txt
collective.tiles.sliders-1.0.0.dist-info/namespace_packages.txt
collective.tiles.sliders-1.0.0.dist-info/top_level.txt
collective.tiles.sliders-1.0.0.dist-info/RECORD
