Metadata-Version: 2.1
Name: collective.tiles.sliders
Version: 1.0.0
Summary: A collection of slider tiles for Mosaic.
Home-page: https://github.com/it-spirit/collective.tiles.sliders
Author: it-spirit
Author-email: development@it-spir.it
License: GPL version 2
Download-URL: https://pypi.python.org/pypi/collective.tiles.sliders
Keywords: Python Plone
Platform: UNKNOWN
Classifier: Development Status :: 4 - Beta
Classifier: Environment :: Web Environment
Classifier: Framework :: Plone
Classifier: Framework :: Plone :: 5.1
Classifier: Intended Audience :: Developers
Classifier: License :: OSI Approved :: GNU General Public License v2 (GPLv2)
Classifier: Programming Language :: Python
Classifier: Programming Language :: Python :: 2.7
Requires-Dist: setuptools
Requires-Dist: Products.GenericSetup (>=1.8.2)
Requires-Dist: plone.api
Requires-Dist: plone.app.tiles
Requires-Dist: plone.tiles
Provides-Extra: mosaic
Requires-Dist: plone.app.mosaic ; extra == 'mosaic'
Provides-Extra: test
Requires-Dist: plone.app.testing ; extra == 'test'
Requires-Dist: plone.testing ; extra == 'test'
Requires-Dist: plone.app.robotframework[debug] ; extra == 'test'
Requires-Dist: robotframework-selenium2screenshots ; extra == 'test'
Requires-Dist: plone.app.mosaic ; extra == 'test'
